pyaicodingcube/__init__.py
pyaicodingcube/aicodingcube.py
pyaicodingcube-0.0.11.dist-info/METADATA
pyaicodingcube-0.0.11.dist-info/WHEEL
pyaicodingcube-0.0.11.dist-info/top_level.txt
pyaicodingcube-0.0.11.dist-info/RECORD
