Metadata-Version: 2.1
Name: pyaicodingcube
Version: 0.0.11
Summary: It is a library for exmarscube
Author: smartcubelabs
Requires-Python: >=3.10
